hypar/__init__.py
hypar/glTF/__init__.py
hypar/glTF/glTF.py
hypar-0.0.6.dist-info/METADATA
hypar-0.0.6.dist-info/RECORD
hypar-0.0.6.dist-info/WHEEL
hypar-0.0.6.dist-info/top_level.txt
