Metadata-Version: 2.1
Name: hypar
Version: 0.0.6
Summary: Function Execution for AEC.
Home-page: https://github.com/hypar-io
Author: Hypar
Author-email: ian@hypar.io
License: MIT
Platform: UNKNOWN
